{
    "nixpkgs": {
        "branch": "nixos-19.09",
        "description": "Nixpkgs/NixOS branches that track the Nixpkgs/NixOS channels",
        "homepage": "https://github.com/NixOS/nixpkgs",
        "owner": "NixOS",
        "repo": "nixpkgs-channels",
        "rev": "d85e435b7bded2596d7b201bcd938c94d8a921c1",
        "sha256": "1msjm4kx1z73v444i1iybvmc7z0kfkbn9nzr21rn5yc4ql1jwf99",
        "type": "tarball",
        "url": "https://github.com/NixOS/nixpkgs-channels/archive/d85e435b7bded2596d7b201bcd938c94d8a921c1.tar.gz",
        "url_template": "https://github.com/<owner>/<repo>/archive/<rev>.tar.gz"
    },
    "termtosvg": {
        "branch": "develop",
        "description": "Record terminal sessions as SVG animations",
        "homepage": "https://nbedos.github.io/termtosvg/",
        "owner": "nbedos",
        "repo": "termtosvg",
        "rev": "b97cc0132073111cec37f64c95539e869202ff99",
        "sha256": "1c86622sda98zm3q3dzwmm37i09yca661kn860svl191nqbh2l68",
        "type": "tarball",
        "url": "https://github.com/nbedos/termtosvg/archive/b97cc0132073111cec37f64c95539e869202ff99.tar.gz",
        "url_template": "https://github.com/<owner>/<repo>/archive/<rev>.tar.gz"
    }
}
